m2_kernel/__init__.py
m2_kernel/__main__.py
m2_kernel/install.py
m2_kernel/kernel.py
m2_kernel/assets/m2-code/init.m2
m2_kernel/assets/m2-mode/macaulay2.js
m2_kernel/assets/m2-mode/main.js
m2_kernel/assets/m2-spec/kernel.js
macaulay2_jupyter_kernel-0.6.7.dist-info/LICENSE
macaulay2_jupyter_kernel-0.6.7.dist-info/METADATA
macaulay2_jupyter_kernel-0.6.7.dist-info/WHEEL
macaulay2_jupyter_kernel-0.6.7.dist-info/top_level.txt
macaulay2_jupyter_kernel-0.6.7.dist-info/RECORD
