Metadata-Version: 2.1
Name: macaulay2-jupyter-kernel
Version: 0.6.7
Summary: Jupyter kernel for Macaulay2
Home-page: https://github.com/radoslavraynov/macaulay2-jupyter-kernel
Author: Radoslav Zlatev
Author-email: radoslav.raynov@yahoo.com
License: UNKNOWN
Platform: UNKNOWN
Classifier: Development Status :: 4 - Beta
Classifier: Programming Language :: Python :: 3.7
Classifier: Operating System :: MacOS :: MacOS X
Classifier: Operating System :: POSIX :: Linux
Classifier: License :: OSI Approved :: MIT License
Requires-Dist: ipykernel
Requires-Dist: notebook
Requires-Dist: pexpect
